parallel_runner/__init__.py
parallel_runner/parallel_runner.py
parallel_runner-0.1.2.dist-info/LICENSE
parallel_runner-0.1.2.dist-info/METADATA
parallel_runner-0.1.2.dist-info/WHEEL
parallel_runner-0.1.2.dist-info/top_level.txt
parallel_runner-0.1.2.dist-info/RECORD
