Metadata-Version: 2.1
Name: parallel-runner
Version: 0.1.2
Summary: A Python utility for running functions in parallel using multiprocessing.
Home-page: https://github.com/msoheili/ParallelRunner
Author: Mohammad Reza Soheili
Author-email: msoheili@gmail.com
Classifier: Programming Language :: Python :: 3
Classifier: License :: OSI Approved :: MIT License
Classifier: Operating System :: OS Independent
Requires-Python: >=3.6
License-File: LICENSE
Requires-Dist: tqdm
